image_px_to_text/__init__.py
image_px_to_text-1.0.1.dist-info/LICENSE
image_px_to_text-1.0.1.dist-info/METADATA
image_px_to_text-1.0.1.dist-info/WHEEL
image_px_to_text-1.0.1.dist-info/top_level.txt
image_px_to_text-1.0.1.dist-info/RECORD
