Metadata-Version: 2.1
Name: image-px-to-text
Version: 1.0.1
Summary: Get the color-info of ALL the pixels in your image
Home-page: https://chaoticcoder.netlify.app
Author: Chaotic Kid
Author-email: crazyanimations999@gmail.com
License: UNKNOWN
Platform: UNKNOWN
Classifier: Programming Language :: Python :: 3
Classifier: License :: OSI Approved :: MIT License
Classifier: Operating System :: OS Independent
Requires-Python: >=3.6
Requires-Dist: Pillow
